redback/__init__.py
redback/analysis.py
redback/constants.py
redback/constraints.py
redback/ejecta_relations.py
redback/eos.py
redback/filters.py
redback/interaction_processes.py
redback/likelihoods.py
redback/model_library.py
redback/photosphere.py
redback/plotting.py
redback/priors.py
redback/redback_errors.py
redback/result.py
redback/sampler.py
redback/sed.py
redback/simulate_transients.py
redback/utils.py
redback/get_data/__init__.py
redback/get_data/batse.py
redback/get_data/directory.py
redback/get_data/fermi.py
redback/get_data/fink.py
redback/get_data/getter.py
redback/get_data/konus.py
redback/get_data/lasair.py
redback/get_data/open_data.py
redback/get_data/swift.py
redback/get_data/utils.py
redback/plot_styles/paper.mplstyle
redback/priors/alternativepowerlaw_redback.prior
redback/priors/alternativepowerlaw_redback_refreshed.prior
redback/priors/arnett.prior
redback/priors/arnett_bolometric.prior
redback/priors/basic_magnetar.prior
redback/priors/basic_magnetar_powered.prior
redback/priors/basic_magnetar_powered_bolometric.prior
redback/priors/basic_mergernova.prior
redback/priors/bazin_sne.prior
redback/priors/blackbody_spectrum_at_z.prior
redback/priors/blackbody_spectrum_with_absorption_and_emission_lines.prior
redback/priors/bpl_cooling_envelope.prior
redback/priors/bulla_bns_kilonova.prior
redback/priors/bulla_nsbh_kilonova.prior
redback/priors/cocoon.prior
redback/priors/collapsing_magnetar.prior
redback/priors/collapsing_radiative_losses.prior
redback/priors/cone_afterglow.prior
redback/priors/cooling_envelope.prior
redback/priors/csm_interaction.prior
redback/priors/csm_nickel.prior
redback/priors/csm_shock_and_arnett.prior
redback/priors/csm_shock_and_arnett_bolometric.prior
redback/priors/csm_shock_and_arnett_two_rphots.prior
redback/priors/csm_shock_breakout.prior
redback/priors/doublegaussian_redback.prior
redback/priors/doublegaussian_redback_refreshed.prior
redback/priors/evolving_magnetar.prior
redback/priors/evolving_magnetar_only.prior
redback-1.12.1.dist-info/licenses/LICENCE.md
redback-1.12.1.dist-info/METADATA
redback-1.12.1.dist-info/WHEEL
redback-1.12.1.dist-info/top_level.txt
redback-1.12.1.dist-info/RECORD
