Metadata-Version: 2.4
Name: redback
Version: 1.12.1
Summary: A Bayesian inference and modelling pipeline for electromagnetic transients
Home-page: https://github.com/nikhil-sarin/redback
Author: Nikhil Sarin, Moritz Huebner
Author-email: nsarin.astro@gmail.com
License: GNU General Public License v3 (GPLv3)
Classifier: Programming Language :: Python :: 3
Classifier: License :: OSI Approved :: GNU General Public License v3 (GPLv3)
Classifier: Operating System :: OS Independent
Requires-Python: >=3.10
License-File: LICENCE.md
Requires-Dist: numpy
Requires-Dist: setuptools
Requires-Dist: pandas
Requires-Dist: scipy
Requires-Dist: selenium
Requires-Dist: matplotlib
Requires-Dist: astropy
Requires-Dist: extinction
Requires-Dist: requests
Requires-Dist: lxml
Requires-Dist: sphinx-rtd-theme
Requires-Dist: sphinx-tabs
Requires-Dist: bilby
Requires-Dist: regex
Requires-Dist: sncosmo
Requires-Dist: afterglowpy
Provides-Extra: all
Requires-Dist: nestle; extra == "all"
Requires-Dist: sherpa; extra == "all"
Requires-Dist: george; extra == "all"
Requires-Dist: scikit-learn; extra == "all"
Requires-Dist: PyQt5; extra == "all"
Requires-Dist: lalsuite; extra == "all"
Requires-Dist: kilonova-heating-rate; extra == "all"
Requires-Dist: redback-surrogates; extra == "all"
Requires-Dist: tensorflow; extra == "all"
Requires-Dist: keras; extra == "all"
Requires-Dist: kilonovanet; extra == "all"
Requires-Dist: astroquery; extra == "all"
Requires-Dist: pyphot==1.6.0; extra == "all"
Dynamic: author
Dynamic: author-email
Dynamic: classifier
Dynamic: description
Dynamic: description-content-type
Dynamic: home-page
Dynamic: license
Dynamic: license-file
Dynamic: provides-extra
Dynamic: requires-dist
Dynamic: requires-python
Dynamic: summary
